decisionforest/__init__.py
decisionforest/config.py
decisionforest/get.py
DecisionForest-1.9.0.dist-info/LICENSE
DecisionForest-1.9.0.dist-info/METADATA
DecisionForest-1.9.0.dist-info/WHEEL
DecisionForest-1.9.0.dist-info/top_level.txt
DecisionForest-1.9.0.dist-info/RECORD
