Metadata-Version: 2.1
Name: DecisionForest
Version: 1.9.0
Summary: Python package for DecisionForest API access
Home-page: https://gitlab.com/decisionforest/decisionforest-python
Author: DecisionForest Ltd
Author-email: admin@decisionforest.com
License: UNKNOWN
Platform: UNKNOWN
Classifier: Programming Language :: Python :: 3
Classifier: License :: OSI Approved :: MIT License
Classifier: Operating System :: OS Independent
